oidc_pt/__init__.py
oidc_pt/run.py
eladpt_oidc_testing-0.0.2.dist-info/METADATA
eladpt_oidc_testing-0.0.2.dist-info/WHEEL
eladpt_oidc_testing-0.0.2.dist-info/top_level.txt
eladpt_oidc_testing-0.0.2.dist-info/RECORD
