Metadata-Version: 2.1
Name: eladpt-oidc-testing
Version: 0.0.2
Summary: Test for OIDC usage
Classifier: Programming Language :: Python :: 3
Classifier: License :: OSI Approved :: MIT License
Classifier: Operating System :: OS Independent
Requires-Python: >=3.9
